withings_api/__init__.py
withings_api/common.py
withings_api/const.py
withings_api-2.4.0.dist-info/LICENSE
withings_api-2.4.0.dist-info/WHEEL
withings_api-2.4.0.dist-info/METADATA
withings_api-2.4.0.dist-info/RECORD
