Metadata-Version: 2.1
Name: withings-api
Version: 2.4.0
Summary: Library for the Withings API
Home-page: https://github.com/vangorra/python_withings_api
License: MIT
Keywords: withings,api
Author: Robbie Van Gorkom
Author-email: robbie.van.gorkom@protonmail.com
Requires-Python: >=3.6,<4.0
Classifier: License :: OSI Approved :: MIT License
Classifier: Programming Language :: Python :: 3
Classifier: Programming Language :: Python :: 3.10
Classifier: Programming Language :: Python :: 3.6
Classifier: Programming Language :: Python :: 3.7
Classifier: Programming Language :: Python :: 3.8
Classifier: Programming Language :: Python :: 3.9
Requires-Dist: arrow (>=1.0.3)
Requires-Dist: pydantic (>=1.7.2,<2.0.0)
Requires-Dist: requests-oauth (>=0.4.1)
Requires-Dist: requests-oauthlib (>=1.2)
Requires-Dist: typing-extensions (>=3.7.4.2)
Project-URL: Repository, https://github.com/vangorra/python_withings_api
